vampireingalaxy/PCA.py
vampireingalaxy/UI_generator.py
vampireingalaxy/__init__.py
vampireingalaxy/bd_resample.py
vampireingalaxy/bdreg.py
vampireingalaxy/clusterSM.py
vampireingalaxy/command_execute.py
vampireingalaxy/command_sort.py
vampireingalaxy/main.py
vampireingalaxy/maskreader.py
vampireingalaxy/masksort.py
vampireingalaxy/pca_bdreg.py
vampireingalaxy/reg_bd3.py
vampireingalaxy/reg_bd_svd.py
vampireingalaxy/test.py
vampireingalaxy/text.py
vampireingalaxy-0.0.19.data/scripts/analysis-run.py
vampireingalaxy-0.0.19.data/scripts/sort-run.py
vampireingalaxy-0.0.19.data/scripts/vampire-run.py
vampireingalaxy-0.0.19.dist-info/METADATA
vampireingalaxy-0.0.19.dist-info/RECORD
vampireingalaxy-0.0.19.dist-info/WHEEL
vampireingalaxy-0.0.19.dist-info/top_level.txt
