Metadata-Version: 2.1
Name: vampireingalaxy
Version: 0.0.19
Summary: Vampire Image Analysis Package
Home-page: https://wirtzlab.johnshopkins.edu
Author: Kyu Sang Han
Author-email: khan21@jhu.edu
License: UNKNOWN
Platform: UNKNOWN
Classifier: Programming Language :: Python :: 2.7
Classifier: License :: OSI Approved :: MIT License
Classifier: Operating System :: MacOS :: MacOS X
Requires-Dist: scipy
Requires-Dist: pandas
Requires-Dist: numpy
Requires-Dist: pillow
Requires-Dist: matplotlib
Requires-Dist: scikit-learn
Requires-Dist: imageio
